fastrag/__init__.py
fastrag/data_loaders.py
fastrag/utils.py
fastrag/agents/__init__.py
fastrag/agents/agent_step.py
fastrag/agents/base.py
fastrag/agents/create_agent.py
fastrag/agents/utils.py
fastrag/agents/memory/__init__.py
fastrag/agents/memory/conversation_memory.py
fastrag/agents/tools/__init__.py
fastrag/agents/tools/tools.py
fastrag/embedders/__init__.py
fastrag/embedders/ipex_embedder.py
fastrag/generators/__init__.py
fastrag/generators/fid.py
fastrag/generators/fid_utils.py
fastrag/generators/gaudi.py
fastrag/generators/gaudi_utils.py
fastrag/generators/ipex.py
fastrag/generators/llava.py
fastrag/generators/openvino.py
fastrag/generators/ort.py
fastrag/generators/replug.py
fastrag/generators/stopping_criteria/__init__.py
fastrag/generators/stopping_criteria/stop_words.py
fastrag/prompt_builders/__init__.py
fastrag/prompt_builders/multi_modal_prompt_builder.py
fastrag/prompt_compressors/__init__.py
fastrag/prompt_compressors/llm_lingua.py
fastrag/prompt_compressors/ov_llm_lingua.py
fastrag/rankers/__init__.py
fastrag/rankers/bi_encoder_ranker.py
fastrag/rankers/colbert.py
fastrag/rankers/ipex_bi_encoder_ranker.py
fastrag/retrievers/__init__.py
fastrag/retrievers/colbert.py
fastrag/stores/__init__.py
fastrag/stores/plaid.py
fastrag/ui/__init__.py
fastrag/ui/chainlit_agent_fastrag_callback.py
fastrag/ui/chainlit_multi_modal.py
fastrag/ui/chainlit_multi_modal_agent.py
fastrag/ui/chainlit_no_rag.py
fastrag/ui/chainlit_pipeline.py
fastrag-3.1.2.dist-info/LICENSE
fastrag-3.1.2.dist-info/METADATA
fastrag-3.1.2.dist-info/WHEEL
fastrag-3.1.2.dist-info/top_level.txt
fastrag-3.1.2.dist-info/RECORD
