Metadata-Version: 2.1
Name: fastrag
Version: 3.1.2
Summary: An Efficient Retrieval Augmentation and Generation Framework for Intel Hardware.
Home-page: https://github.com/IntelLabs/fastRAG
Author: Intel Labs
License: Apache-2.0
Classifier: Programming Language :: Python :: 3
Classifier: License :: OSI Approved :: Apache Software License
Classifier: Operating System :: OS Independent
Classifier: Topic :: Scientific/Engineering :: Artificial Intelligence
Classifier: Topic :: Software Development :: Libraries
Requires-Python: >=3.8, <3.12
License-File: LICENSE
Requires-Dist: haystack-ai>=2.1.2
Requires-Dist: transformers>=4.35.2
Requires-Dist: datasets
Requires-Dist: evaluate
Requires-Dist: pandas
Requires-Dist: nltk
Requires-Dist: tqdm
Requires-Dist: numba
Requires-Dist: openpyxl
Requires-Dist: numpy
Requires-Dist: protobuf>=5.28.3
Requires-Dist: ujson
Requires-Dist: accelerate
Requires-Dist: fastapi
Requires-Dist: uvicorn
Requires-Dist: Pillow>=10.1.0
Requires-Dist: chainlit>=1.0.506
Requires-Dist: sentence-transformers>=2.3.0
Requires-Dist: events
Provides-Extra: dev
Requires-Dist: black; extra == "dev"
Requires-Dist: isort; extra == "dev"
Requires-Dist: pytest; extra == "dev"
Requires-Dist: pre-commit; extra == "dev"
Provides-Extra: elastic
Requires-Dist: elasticsearch-haystack; extra == "elastic"
Provides-Extra: colbert
Requires-Dist: colbert-ai; extra == "colbert"
Provides-Extra: faiss-gpu
Requires-Dist: faiss-gpu; extra == "faiss-gpu"
Provides-Extra: faiss-cpu
Requires-Dist: faiss-cpu; extra == "faiss-cpu"
Provides-Extra: qdrant
Requires-Dist: qdrant-haystack>=3.2.0; extra == "qdrant"
Provides-Extra: quantize-reranker
Requires-Dist: opencv-python-headless; extra == "quantize-reranker"
Requires-Dist: intel-extension-for-transformers==1.1; extra == "quantize-reranker"
Requires-Dist: neural_compressor==2.1.1; extra == "quantize-reranker"
Requires-Dist: pytrec_eval; extra == "quantize-reranker"
Requires-Dist: transformers>=4.28.1; extra == "quantize-reranker"
Requires-Dist: datasets>=1.8.0; extra == "quantize-reranker"
Requires-Dist: sentencepiece!=0.1.92; extra == "quantize-reranker"
Requires-Dist: protobuf==5.28.3; extra == "quantize-reranker"
Requires-Dist: torch==1.13.1; extra == "quantize-reranker"
Requires-Dist: onnx==1.14.0; extra == "quantize-reranker"
Requires-Dist: onnxruntime==1.13.1; extra == "quantize-reranker"
Requires-Dist: onnxruntime-extensions==0.8.0; extra == "quantize-reranker"
Requires-Dist: sentence-transformers==2.2.2; extra == "quantize-reranker"
Provides-Extra: intel
Requires-Dist: intel-extension-for-pytorch; extra == "intel"
Requires-Dist: optimum[ipex,neural-compressor]; extra == "intel"
Provides-Extra: llama-cpp
Requires-Dist: llama-cpp-python; extra == "llama-cpp"
Provides-Extra: openvino
Requires-Dist: optimum[nncf,openvino]; extra == "openvino"
Requires-Dist: openvino; extra == "openvino"
Provides-Extra: llmlingua
Requires-Dist: llmlingua; extra == "llmlingua"
Provides-Extra: habana
Requires-Dist: optimum[habana]; extra == "habana"
